Metadata-Version: 2.4
Name: ezfastq
Version: 0.1.1
Summary: Scan directories for FASTQ files and associate with sample names
Author-email: Daniel Standage <daniel.standage@st.dhs.gov>, Ryan Berger <ryan.berger@st.dhs.gov>
Requires-Python: >=3.10
License-File: LICENSE.txt
Requires-Dist: rich
Dynamic: license-file
